dsalib/__init__.py
dsalib/Array/__init__.py
dsalib/Array/insert.py
dsalib/Array/remove.py
dsalib/Array/search.py
dsalib/Array/sort.py
dsalib/Queue/Queue.py
dsalib/Queue/__init__.py
dsalib/Search/__init__.py
dsalib/Search/binary_search.py
dsalib/Search/linear_search.py
dsalib/Sorting/__init__.py
dsalib/Sorting/bubble_sort.py
dsalib/Sorting/insertion_sort.py
dsalib/Sorting/merge_sort.py
dsalib/Sorting/selection_sort.py
dsalib/Stack/Stack.py
dsalib/Stack/__init__.py
dsalib-0.0.33.dist-info/LICENSE.txt
dsalib-0.0.33.dist-info/METADATA
dsalib-0.0.33.dist-info/WHEEL
dsalib-0.0.33.dist-info/top_level.txt
dsalib-0.0.33.dist-info/RECORD
