Metadata-Version: 2.1
Name: dsalib
Version: 0.0.33
Summary: Data Structures and Algorithms In Python
Home-page: https://github.com/rajeshberwal/dsalib
Author: Rajesh Berwal
Author-email: irajeshberwal@gmail.com
License: UNKNOWN
Platform: UNKNOWN
Classifier: Programming Language :: Python :: 3
Classifier: License :: OSI Approved :: MIT License
Classifier: Operating System :: OS Independent
Requires-Python: >=3.6
